{
  "db_name": "SQLite",
  "query": "SELECT id         as \"id!: Uuid\",\n                      comment_id as \"comment_id!: Uuid\",\n                      user_id    as \"user_id!: Uuid\",\n                      emoji,\n                      created_at as \"created_at!: DateTime<Utc>\"\n               FROM issue_comment_reactions\n               WHERE comment_id = $1\n               ORDER BY created_at ASC",
  "describe": {
    "columns": [
      {
        "name": "id!: Uuid",
        "ordinal": 0,
        "type_info": "Blob"
      },
      {
        "name": "comment_id!: Uuid",
        "ordinal": 1,
        "type_info": "Blob"
      },
      {
        "name": "user_id!: Uuid",
        "ordinal": 2,
        "type_info": "Blob"
      },
      {
        "name": "emoji",
        "ordinal": 3,
        "type_info": "Text"
      },
      {
        "name": "created_at!: DateTime<Utc>",
        "ordinal": 4,
        "type_info": "Text"
      }
    ],
    "parameters": {
      "Right": 1
    },
    "nullable": [
      true,
      false,
      false,
      false,
      false
    ]
  },
  "hash": "9c6960238f0a55ec786cbd430c2a07dfb5b354719922aeb5bd779f5f2a824aa8"
}
